AUTHORS
CHANGELOG.txt
DESCRIPTION
LICENSE
MANIFEST.in
README.rst
setup.py
django_enquiry.egg-info/PKG-INFO
django_enquiry.egg-info/SOURCES.txt
django_enquiry.egg-info/dependency_links.txt
django_enquiry.egg-info/top_level.txt
enquiry/__init__.py
enquiry/admin.py
enquiry/cms_app.py
enquiry/forms.py
enquiry/models.py
enquiry/simple_translate.py
enquiry/urls.py
enquiry/views.py
enquiry/fixtures/bootstrap.json
enquiry/migrations/0001_initial.py
enquiry/migrations/0002_auto__chg_field_vote_user.py
enquiry/migrations/0003_auto__add_field_vote_session_key.py
enquiry/migrations/0004_auto__add_field_enquirytrans_description__chg_field_enquiry_end_date.py
enquiry/migrations/0005_auto__add_field_enquirytrans_extra_info.py
enquiry/migrations/0006_auto__chg_field_enquiry_created_by.py
enquiry/migrations/0007_auto__add_field_enquiry_is_published.py
enquiry/migrations/__init__.py
enquiry/templates/404.html
enquiry/templates/base.html
enquiry/templates/enquiry/current_poll.html
enquiry/templates/enquiry/enquiry_detail.html
enquiry/templates/enquiry/enquiry_list.html
enquiry/templates/enquiry/vote_form.html
enquiry/templatetags/__init__.py
enquiry/templatetags/enquiry_tags.py
enquiry/tests/__init__.py
enquiry/tests/factories.py
enquiry/tests/models_tests.py
enquiry/tests/runtests.py
enquiry/tests/south_settings.py
enquiry/tests/tags_tests.py
enquiry/tests/test_settings.py
enquiry/tests/urls.py
enquiry/tests/integration_tests/views_tests.py