Metadata-Version: 1.0
Name: django-enquiry
Version: 0.7.1
Summary: A simple multilingual poll app.
